clockwork/clockwork.py
clockwork/clockwork_exceptions.py
clockwork/clockwork_http.py
clockwork/__init__.py
Clockwork-1.1.0.dist-info/DESCRIPTION.rst
Clockwork-1.1.0.dist-info/METADATA
Clockwork-1.1.0.dist-info/metadata.json
Clockwork-1.1.0.dist-info/RECORD
Clockwork-1.1.0.dist-info/top_level.txt
Clockwork-1.1.0.dist-info/WHEEL
