Metadata-Version: 2.0
Name: Clockwork
Version: 1.1.0
Summary: Python wrapper for the clockwork SMS Api
Home-page: https://github.com/mediaburst/clockwork-python
Author: Mediaburst
Author-email: hello@clockworksms.com
License: MIT
Platform: UNKNOWN
Requires-Dist: lxml
